[{"sampleNumber":15,"time":0,"beat":1},{"sampleNumber":24007,"time":500,"beat":2},{"sampleNumber":48015,"time":1000,"beat":1},{"sampleNumber":72007,"time":1500,"beat":2},{"sampleNumber":96015,"time":2000,"beat":1},{"sampleNumber":120007,"time":2500,"beat":2},{"sampleNumber":144015,"time":3000,"beat":1},{"sampleNumber":168007,"time":3500,"beat":2},{"sampleNumber":192015,"time":4000,"beat":1},{"sampleNumber":216007,"time":4500,"beat":2},{"sampleNumber":240015,"time":5000,"beat":1},{"sampleNumber":264007,"time":5500,"beat":2},{"sampleNumber":288015,"time":6000,"beat":1},{"sampleNumber":312007,"time":6500,"beat":2},{"sampleNumber":336015,"time":7000,"beat":1},{"sampleNumber":360007,"time":7500,"beat":2},{"sampleNumber":384015,"time":8000,"beat":1},{"sampleNumber":408007,"time":8500,"beat":2},{"sampleNumber":432015,"time":9000,"beat":1},{"sampleNumber":456007,"time":9500,"beat":2},{"sampleNumber":480015,"time":10000,"beat":1},{"sampleNumber":504007,"time":10500,"beat":2},{"sampleNumber":528015,"time":11000,"beat":1},{"sampleNumber":552007,"time":11500,"beat":2},{"sampleNumber":576015,"time":12000,"beat":1},{"sampleNumber":600007,"time":12500,"beat":2},{"sampleNumber":624015,"time":13000,"beat":1},{"sampleNumber":648007,"time":13500,"beat":2},{"sampleNumber":672015,"time":14000,"beat":1},{"sampleNumber":696007,"time":14500,"beat":2},{"sampleNumber":720007,"time":15000,"beat":3},{"sampleNumber":744015,"time":15500,"beat":1},{"sampleNumber":768007,"time":16000,"beat":2},{"sampleNumber":792007,"time":16500,"beat":3},{"sampleNumber":816015,"time":17000,"beat":1},{"sampleNumber":840007,"time":17500,"beat":2},{"sampleNumber":864007,"time":18000,"beat":3},{"sampleNumber":888015,"time":18500,"beat":1},{"sampleNumber":912007,"time":19000,"beat":2},{"sampleNumber":936007,"time":19500,"beat":3},{"sampleNumber":960015,"time":20000,"beat":1},{"sampleNumber":984007,"time":20500,"beat":2},{"sampleNumber":1008007,"time":21000,"beat":3},{"sampleNumber":1032015,"time":21500,"beat":1},{"sampleNumber":1056007,"time":22000,"beat":2},{"sampleNumber":1080007,"time":22500,"beat":3},{"sampleNumber":1104015,"time":23000,"beat":1},{"sampleNumber":1128007,"time":23500,"beat":2},{"sampleNumber":1152007,"time":24000,"beat":3},{"sampleNumber":1176015,"time":24500,"beat":1},{"sampleNumber":1200007,"time":25000,"beat":2}]