[{"sampleNumber":7,"time":0,"beat":2},{"sampleNumber":80015,"time":1667,"beat":1},{"sampleNumber":160006,"time":3333,"beat":2},{"sampleNumber":240006,"time":5000,"beat":3},{"sampleNumber":320013,"time":6667,"beat":1},{"sampleNumber":400005,"time":8333,"beat":2},{"sampleNumber":480004,"time":10000,"beat":3},{"sampleNumber":560012,"time":11667,"beat":1},{"sampleNumber":640003,"time":13333,"beat":2},{"sampleNumber":720003,"time":15000,"beat":3},{"sampleNumber":800011,"time":16667,"beat":1},{"sampleNumber":880002,"time":18333,"beat":2},{"sampleNumber":960002,"time":20000,"beat":3},{"sampleNumber":1040009,"time":21667,"beat":1},{"sampleNumber":1120001,"time":23333,"beat":2},{"sampleNumber":1200000,"time":25000,"beat":3},{"sampleNumber":1280008,"time":26667,"beat":1},{"sampleNumber":1359999,"time":28333,"beat":2},{"sampleNumber":1439999,"time":30000,"beat":3},{"sampleNumber":1520006,"time":31667,"beat":1},{"sampleNumber":1599998,"time":33333,"beat":2},{"sampleNumber":1679998,"time":35000,"beat":3},{"sampleNumber":1760005,"time":36667,"beat":1},{"sampleNumber":1839997,"time":38333,"beat":2},{"sampleNumber":1919996,"time":40000,"beat":3},{"sampleNumber":2000004,"time":41667,"beat":1},{"sampleNumber":2079996,"time":43333,"beat":2},{"sampleNumber":2159995,"time":45000,"beat":3}]