[{"sampleNumber":32743,"time":682,"beat":1},{"sampleNumber":105661,"time":2201,"beat":2},{"sampleNumber":185865,"time":3872,"beat":3},{"sampleNumber":261092,"time":5439,"beat":1},{"sampleNumber":327700,"time":6827,"beat":2},{"sampleNumber":393155,"time":8191,"beat":3},{"sampleNumber":458617,"time":9555,"beat":1},{"sampleNumber":524064,"time":10918,"beat":2},{"sampleNumber":589519,"time":12282,"beat":3},{"sampleNumber":654981,"time":13645,"beat":1},{"sampleNumber":720428,"time":15009,"beat":2},{"sampleNumber":786015,"time":16375,"beat":3},{"sampleNumber":877245,"time":18276,"beat":1},{"sampleNumber":952578,"time":19845,"beat":2},{"sampleNumber":1018033,"time":21209,"beat":3},{"sampleNumber":1083495,"time":22573,"beat":1},{"sampleNumber":1148942,"time":23936,"beat":2},{"sampleNumber":1214396,"time":25300,"beat":3},{"sampleNumber":1279859,"time":26664,"beat":1},{"sampleNumber":1345305,"time":28027,"beat":2},{"sampleNumber":1410760,"time":29391,"beat":3},{"sampleNumber":1479519,"time":30823,"beat":1},{"sampleNumber":1555854,"time":32414,"beat":2},{"sampleNumber":1631608,"time":33992,"beat":3},{"sampleNumber":1719449,"time":35822,"beat":1},{"sampleNumber":1784895,"time":37185,"beat":2},{"sampleNumber":1850350,"time":38549,"beat":3},{"sampleNumber":1915813,"time":39913,"beat":1},{"sampleNumber":1981259,"time":41276,"beat":2},{"sampleNumber":2046714,"time":42640,"beat":3},{"sampleNumber":2112176,"time":44004,"beat":1},{"sampleNumber":2177623,"time":45367,"beat":2},{"sampleNumber":2243077,"time":46731,"beat":3},{"sampleNumber":2308540,"time":48095,"beat":1},{"sampleNumber":2373986,"time":49458,"beat":2},{"sampleNumber":2439441,"time":50822,"beat":3},{"sampleNumber":2504904,"time":52186,"beat":1},{"sampleNumber":2570350,"time":53549,"beat":2},{"sampleNumber":2635805,"time":54913,"beat":3},{"sampleNumber":2701267,"time":56276,"beat":1},{"sampleNumber":2766714,"time":57640,"beat":2},{"sampleNumber":2832168,"time":59004,"beat":3},{"sampleNumber":2897631,"time":60367,"beat":1},{"sampleNumber":2963078,"time":61731,"beat":2},{"sampleNumber":3028532,"time":63094,"beat":3},{"sampleNumber":3093995,"time":64458,"beat":1},{"sampleNumber":3159441,"time":65822,"beat":2},{"sampleNumber":3232368,"time":67341,"beat":3},{"sampleNumber":3308032,"time":68917,"beat":1},{"sampleNumber":3375668,"time":70326,"beat":2},{"sampleNumber":3451217,"time":71900,"beat":3},{"sampleNumber":3542487,"time":73802,"beat":1},{"sampleNumber":3610802,"time":75225,"beat":2},{"sampleNumber":3676257,"time":76589,"beat":3},{"sampleNumber":3746746,"time":78057,"beat":1},{"sampleNumber":3817218,"time":79525,"beat":2},{"sampleNumber":3882673,"time":80889,"beat":3},{"sampleNumber":3948135,"time":82253,"beat":1},{"sampleNumber":4013582,"time":83616,"beat":2},{"sampleNumber":4079036,"time":84980,"beat":3},{"sampleNumber":4144499,"time":86344,"beat":1},{"sampleNumber":4215568,"time":87824,"beat":2},{"sampleNumber":4288619,"time":89346,"beat":3},{"sampleNumber":4358973,"time":90812,"beat":1},{"sampleNumber":4436007,"time":92417,"beat":2},{"sampleNumber":4505627,"time":93867,"beat":3},{"sampleNumber":4572402,"time":95258,"beat":1},{"sampleNumber":4637849,"time":96622,"beat":2},{"sampleNumber":4703303,"time":97985,"beat":3},{"sampleNumber":4768766,"time":99349,"beat":1},{"sampleNumber":4834213,"time":100713,"beat":2},{"sampleNumber":4899667,"time":102076,"beat":3},{"sampleNumber":4965130,"time":103440,"beat":1},{"sampleNumber":5030576,"time":104804,"beat":2},{"sampleNumber":5096031,"time":106167,"beat":3},{"sampleNumber":5161493,"time":107531,"beat":1},{"sampleNumber":5226940,"time":108895,"beat":2},{"sampleNumber":5292395,"time":110258,"beat":3},{"sampleNumber":5370456,"time":111885,"beat":1},{"sampleNumber":5434669,"time":113222,"beat":2},{"sampleNumber":5499706,"time":114577,"beat":3},{"sampleNumber":5574483,"time":116135,"beat":1},{"sampleNumber":5659291,"time":117902,"beat":2},{"sampleNumber":5747675,"time":119743,"beat":3},{"sampleNumber":5902009,"time":122959,"beat":1},{"sampleNumber":6037669,"time":125785,"beat":2},{"sampleNumber":6114658,"time":127389,"beat":3}]