[{"sampleNumber":40015,"time":834,"beat":1},{"sampleNumber":129140,"time":2690,"beat":2},{"sampleNumber":227166,"time":4733,"beat":3},{"sampleNumber":319108,"time":6648,"beat":1},{"sampleNumber":400521,"time":8344,"beat":2},{"sampleNumber":480520,"time":10011,"beat":3},{"sampleNumber":560528,"time":11678,"beat":1},{"sampleNumber":640520,"time":13344,"beat":2},{"sampleNumber":720520,"time":15011,"beat":3},{"sampleNumber":800528,"time":16678,"beat":1},{"sampleNumber":880520,"time":18344,"beat":2},{"sampleNumber":960684,"time":20014,"beat":3},{"sampleNumber":1072184,"time":22337,"beat":1},{"sampleNumber":1164259,"time":24255,"beat":2},{"sampleNumber":1244259,"time":25922,"beat":3},{"sampleNumber":1324267,"time":27589,"beat":1},{"sampleNumber":1404259,"time":29255,"beat":2},{"sampleNumber":1484259,"time":30922,"beat":3},{"sampleNumber":1564267,"time":32589,"beat":1},{"sampleNumber":1644259,"time":34255,"beat":2},{"sampleNumber":1724259,"time":35922,"beat":3},{"sampleNumber":1808296,"time":37673,"beat":1},{"sampleNumber":1901596,"time":39617,"beat":2},{"sampleNumber":1994184,"time":41546,"beat":3},{"sampleNumber":2101543,"time":43782,"beat":1},{"sampleNumber":2181535,"time":45449,"beat":2},{"sampleNumber":2261535,"time":47115,"beat":3},{"sampleNumber":2341543,"time":48782,"beat":1},{"sampleNumber":2421535,"time":50449,"beat":2},{"sampleNumber":2501535,"time":52115,"beat":3},{"sampleNumber":2581543,"time":53782,"beat":1},{"sampleNumber":2661535,"time":55449,"beat":2},{"sampleNumber":2741535,"time":57115,"beat":3},{"sampleNumber":2821543,"time":58782,"beat":1},{"sampleNumber":2901534,"time":60449,"beat":2},{"sampleNumber":2981534,"time":62115,"beat":3},{"sampleNumber":3061542,"time":63782,"beat":1},{"sampleNumber":3141534,"time":65449,"beat":2},{"sampleNumber":3221534,"time":67115,"beat":3},{"sampleNumber":3301542,"time":68782,"beat":1},{"sampleNumber":3381534,"time":70449,"beat":2},{"sampleNumber":3461534,"time":72115,"beat":3},{"sampleNumber":3541542,"time":73782,"beat":1},{"sampleNumber":3621534,"time":75449,"beat":2},{"sampleNumber":3701534,"time":77115,"beat":3},{"sampleNumber":3781542,"time":78782,"beat":1},{"sampleNumber":3861534,"time":80449,"beat":2},{"sampleNumber":3950666,"time":82306,"beat":3},{"sampleNumber":4043142,"time":84232,"beat":1},{"sampleNumber":4125811,"time":85954,"beat":2},{"sampleNumber":4218148,"time":87878,"beat":3},{"sampleNumber":4329698,"time":90202,"beat":1},{"sampleNumber":4413197,"time":91942,"beat":2},{"sampleNumber":4493197,"time":93608,"beat":3},{"sampleNumber":4579348,"time":95403,"beat":1},{"sampleNumber":4665482,"time":97198,"beat":2},{"sampleNumber":4745482,"time":98864,"beat":3},{"sampleNumber":4825490,"time":100531,"beat":1},{"sampleNumber":4905482,"time":102198,"beat":2},{"sampleNumber":4985482,"time":103864,"beat":3},{"sampleNumber":5065490,"time":105531,"beat":1},{"sampleNumber":5152354,"time":107341,"beat":2},{"sampleNumber":5241639,"time":109201,"beat":3},{"sampleNumber":5327625,"time":110992,"beat":1},{"sampleNumber":5421780,"time":112954,"beat":2},{"sampleNumber":5506870,"time":114726,"beat":3},{"sampleNumber":5588483,"time":116427,"beat":1},{"sampleNumber":5668475,"time":118093,"beat":2},{"sampleNumber":5748475,"time":119760,"beat":3},{"sampleNumber":5828482,"time":121427,"beat":1},{"sampleNumber":5908474,"time":123093,"beat":2},{"sampleNumber":5988474,"time":124760,"beat":3},{"sampleNumber":6068482,"time":126427,"beat":1},{"sampleNumber":6148474,"time":128093,"beat":2},{"sampleNumber":6228474,"time":129760,"beat":3},{"sampleNumber":6308482,"time":131427,"beat":1},{"sampleNumber":6388474,"time":133093,"beat":2},{"sampleNumber":6468474,"time":134760,"beat":3},{"sampleNumber":6563880,"time":136748,"beat":1},{"sampleNumber":6642365,"time":138383,"beat":2},{"sampleNumber":6721855,"time":140039,"beat":3},{"sampleNumber":6813247,"time":141943,"beat":1},{"sampleNumber":6916903,"time":144102,"beat":2},{"sampleNumber":7024927,"time":146353,"beat":3},{"sampleNumber":7213556,"time":150282,"beat":1},{"sampleNumber":7379364,"time":153737,"beat":2},{"sampleNumber":7473463,"time":155697,"beat":3}]