[{"sampleNumber":283,"time":6,"beat":2},{"sampleNumber":24283,"time":506,"beat":3},{"sampleNumber":49723,"time":1036,"beat":4},{"sampleNumber":75163,"time":1566,"beat":5},{"sampleNumber":100603,"time":2096,"beat":6},{"sampleNumber":126523,"time":2636,"beat":7},{"sampleNumber":152442,"time":3176,"beat":8},{"sampleNumber":178362,"time":3716,"beat":9},{"sampleNumber":203802,"time":4246,"beat":10},{"sampleNumber":229242,"time":4776,"beat":11},{"sampleNumber":254203,"time":5296,"beat":12},{"sampleNumber":279643,"time":5826,"beat":13},{"sampleNumber":305083,"time":6356,"beat":14},{"sampleNumber":330523,"time":6886,"beat":15},{"sampleNumber":356442,"time":7426,"beat":16},{"sampleNumber":382362,"time":7966,"beat":17},{"sampleNumber":407802,"time":8496,"beat":18},{"sampleNumber":434203,"time":9046,"beat":19},{"sampleNumber":459643,"time":9576,"beat":20},{"sampleNumber":485562,"time":10116,"beat":21},{"sampleNumber":511482,"time":10656,"beat":22},{"sampleNumber":536922,"time":11186,"beat":23},{"sampleNumber":562362,"time":11716,"beat":24},{"sampleNumber":588283,"time":12256,"beat":25},{"sampleNumber":614203,"time":12796,"beat":26},{"sampleNumber":639643,"time":13326,"beat":27},{"sampleNumber":666043,"time":13876,"beat":28},{"sampleNumber":691002,"time":14396,"beat":29},{"sampleNumber":715963,"time":14916,"beat":30},{"sampleNumber":742843,"time":15476,"beat":31},{"sampleNumber":767802,"time":15996,"beat":32},{"sampleNumber":793242,"time":16526,"beat":33},{"sampleNumber":817723,"time":17036,"beat":34},{"sampleNumber":844122,"time":17586,"beat":35},{"sampleNumber":869562,"time":18116,"beat":36},{"sampleNumber":895002,"time":18646,"beat":37},{"sampleNumber":919482,"time":19156,"beat":38},{"sampleNumber":944922,"time":19686,"beat":39},{"sampleNumber":970362,"time":20216,"beat":40},{"sampleNumber":996283,"time":20756,"beat":41},{"sampleNumber":1022203,"time":21296,"beat":42},{"sampleNumber":1047163,"time":21816,"beat":43},{"sampleNumber":1072122,"time":22336,"beat":44},{"sampleNumber":1098043,"time":22876,"beat":45},{"sampleNumber":1123963,"time":23416,"beat":46},{"sampleNumber":1149882,"time":23956,"beat":47},{"sampleNumber":1175322,"time":24486,"beat":48},{"sampleNumber":1200283,"time":25006,"beat":49},{"sampleNumber":1224763,"time":25516,"beat":50},{"sampleNumber":1250203,"time":26046,"beat":51},{"sampleNumber":1276122,"time":26586,"beat":52},{"sampleNumber":1302043,"time":27126,"beat":53},{"sampleNumber":1327963,"time":27666,"beat":54},{"sampleNumber":1355322,"time":28236,"beat":55},{"sampleNumber":1381242,"time":28776,"beat":56},{"sampleNumber":1407643,"time":29326,"beat":57},{"sampleNumber":1434523,"time":29886,"beat":58},{"sampleNumber":1460922,"time":30436,"beat":59},{"sampleNumber":1487802,"time":30996,"beat":60},{"sampleNumber":1513242,"time":31526,"beat":61},{"sampleNumber":1539643,"time":32076,"beat":62},{"sampleNumber":1567002,"time":32646,"beat":63},{"sampleNumber":1594362,"time":33216,"beat":64},{"sampleNumber":1621242,"time":33776,"beat":65},{"sampleNumber":1647163,"time":34316,"beat":66},{"sampleNumber":1674523,"time":34886,"beat":67},{"sampleNumber":1699963,"time":35416,"beat":68},{"sampleNumber":1726843,"time":35976,"beat":69},{"sampleNumber":1753242,"time":36526,"beat":70},{"sampleNumber":1779643,"time":37076,"beat":71},{"sampleNumber":1805562,"time":37616,"beat":72},{"sampleNumber":1832922,"time":38186,"beat":73},{"sampleNumber":1858843,"time":38726,"beat":74},{"sampleNumber":1884763,"time":39266,"beat":75},{"sampleNumber":1912603,"time":39846,"beat":76},{"sampleNumber":1939002,"time":40396,"beat":77},{"sampleNumber":1965882,"time":40956,"beat":78},{"sampleNumber":1992283,"time":41506,"beat":79},{"sampleNumber":2019643,"time":42076,"beat":80},{"sampleNumber":2046523,"time":42636,"beat":81},{"sampleNumber":2072922,"time":43186,"beat":82},{"sampleNumber":2098843,"time":43726,"beat":83},{"sampleNumber":2125723,"time":44286,"beat":84},{"sampleNumber":2153083,"time":44856,"beat":85},{"sampleNumber":2179482,"time":45406,"beat":86},{"sampleNumber":2206843,"time":45976,"beat":87},{"sampleNumber":2233242,"time":46526,"beat":88},{"sampleNumber":2260122,"time":47086,"beat":89},{"sampleNumber":2287002,"time":47646,"beat":90},{"sampleNumber":2314843,"time":48226,"beat":91},{"sampleNumber":2340763,"time":48766,"beat":92},{"sampleNumber":2367643,"time":49326,"beat":93},{"sampleNumber":2394523,"time":49886,"beat":94},{"sampleNumber":2422362,"time":50466,"beat":95},{"sampleNumber":2448763,"time":51016,"beat":96},{"sampleNumber":2476603,"time":51596,"beat":97},{"sampleNumber":2502523,"time":52136,"beat":98},{"sampleNumber":2529882,"time":52706,"beat":99},{"sampleNumber":2556763,"time":53266,"beat":100},{"sampleNumber":2584122,"time":53836,"beat":101},{"sampleNumber":2611002,"time":54396,"beat":102},{"sampleNumber":2637882,"time":54956,"beat":103},{"sampleNumber":2664763,"time":55516,"beat":104},{"sampleNumber":2691643,"time":56076,"beat":105},{"sampleNumber":2717562,"time":56616,"beat":106},{"sampleNumber":2745403,"time":57196,"beat":107},{"sampleNumber":2772283,"time":57756,"beat":108},{"sampleNumber":2798203,"time":58296,"beat":109},{"sampleNumber":2826043,"time":58876,"beat":110},{"sampleNumber":2851963,"time":59416,"beat":111},{"sampleNumber":2879802,"time":59996,"beat":112},{"sampleNumber":2906682,"time":60556,"beat":113},{"sampleNumber":2933562,"time":61116,"beat":114},{"sampleNumber":2960442,"time":61676,"beat":115},{"sampleNumber":2987322,"time":62236,"beat":116},{"sampleNumber":3013242,"time":62776,"beat":117},{"sampleNumber":3039643,"time":63326,"beat":118},{"sampleNumber":3066523,"time":63886,"beat":119},{"sampleNumber":3093403,"time":64446,"beat":120},{"sampleNumber":3120283,"time":65006,"beat":121},{"sampleNumber":3148122,"time":65586,"beat":122},{"sampleNumber":3175002,"time":66146,"beat":123},{"sampleNumber":3205723,"time":66786,"beat":124},{"sampleNumber":3235002,"time":67396,"beat":125},{"sampleNumber":3264283,"time":68006,"beat":126},{"sampleNumber":3293562,"time":68616,"beat":127},{"sampleNumber":3324763,"time":69266,"beat":128},{"sampleNumber":3353562,"time":69866,"beat":129},{"sampleNumber":3385242,"time":70526,"beat":130},{"sampleNumber":3415482,"time":71156,"beat":131},{"sampleNumber":3445723,"time":71786,"beat":132},{"sampleNumber":3474523,"time":72386,"beat":133},{"sampleNumber":3506203,"time":73046,"beat":134},{"sampleNumber":3536442,"time":73676,"beat":135},{"sampleNumber":3565242,"time":74276,"beat":136},{"sampleNumber":3595482,"time":74906,"beat":137},{"sampleNumber":3625723,"time":75536,"beat":138},{"sampleNumber":3657403,"time":76196,"beat":139},{"sampleNumber":3687643,"time":76826,"beat":140},{"sampleNumber":3717882,"time":77456,"beat":141},{"sampleNumber":3747643,"time":78076,"beat":142},{"sampleNumber":3777403,"time":78696,"beat":143},{"sampleNumber":3808122,"time":79336,"beat":144},{"sampleNumber":3838843,"time":79976,"beat":145},{"sampleNumber":3867643,"time":80576,"beat":146},{"sampleNumber":3897882,"time":81206,"beat":147},{"sampleNumber":3928603,"time":81846,"beat":148},{"sampleNumber":3959802,"time":82496,"beat":149},{"sampleNumber":3989562,"time":83116,"beat":150},{"sampleNumber":4019802,"time":83746,"beat":151},{"sampleNumber":4049083,"time":84356,"beat":152},{"sampleNumber":4080763,"time":85016,"beat":153},{"sampleNumber":4109562,"time":85616,"beat":154},{"sampleNumber":4141242,"time":86276,"beat":155},{"sampleNumber":4171002,"time":86896,"beat":156},{"sampleNumber":4200283,"time":87506,"beat":157},{"sampleNumber":4230523,"time":88136,"beat":158},{"sampleNumber":4260763,"time":88766,"beat":159},{"sampleNumber":4291963,"time":89416,"beat":160},{"sampleNumber":4321242,"time":90026,"beat":161},{"sampleNumber":4352922,"time":90686,"beat":162},{"sampleNumber":4383163,"time":91316,"beat":163},{"sampleNumber":4414843,"time":91976,"beat":164}]