[{"sampleNumber":7,"time":0,"beat":2},{"sampleNumber":45269,"time":943,"beat":1},{"sampleNumber":91972,"time":1916,"beat":2},{"sampleNumber":133714,"time":2786,"beat":3},{"sampleNumber":174857,"time":3643,"beat":4},{"sampleNumber":217859,"time":4539,"beat":1},{"sampleNumber":260845,"time":5434,"beat":2},{"sampleNumber":301988,"time":6291,"beat":3},{"sampleNumber":343130,"time":7149,"beat":4},{"sampleNumber":385233,"time":8026,"beat":1},{"sampleNumber":429416,"time":8946,"beat":2},{"sampleNumber":476052,"time":9918,"beat":3},{"sampleNumber":524052,"time":10918,"beat":4},{"sampleNumber":572059,"time":11918,"beat":1},{"sampleNumber":620051,"time":12918,"beat":2},{"sampleNumber":668050,"time":13918,"beat":3},{"sampleNumber":716050,"time":14918,"beat":4},{"sampleNumber":764049,"time":15918,"beat":5},{"sampleNumber":817821,"time":17038,"beat":6},{"sampleNumber":888037,"time":18501,"beat":1},{"sampleNumber":961653,"time":20034,"beat":2}]