[{"sampleNumber":26323,"time":548,"beat":1},{"sampleNumber":54008,"time":1125,"beat":2},{"sampleNumber":81708,"time":1702,"beat":1},{"sampleNumber":109392,"time":2279,"beat":2},{"sampleNumber":137093,"time":2856,"beat":1},{"sampleNumber":164777,"time":3433,"beat":2},{"sampleNumber":192478,"time":4010,"beat":1},{"sampleNumber":220162,"time":4587,"beat":2},{"sampleNumber":247862,"time":5164,"beat":1},{"sampleNumber":275547,"time":5741,"beat":2},{"sampleNumber":303247,"time":6318,"beat":1},{"sampleNumber":330932,"time":6894,"beat":2},{"sampleNumber":358632,"time":7472,"beat":1},{"sampleNumber":386316,"time":8048,"beat":2},{"sampleNumber":414017,"time":8625,"beat":1},{"sampleNumber":441701,"time":9202,"beat":2},{"sampleNumber":469402,"time":9779,"beat":1},{"sampleNumber":497086,"time":10356,"beat":2},{"sampleNumber":524786,"time":10933,"beat":1},{"sampleNumber":552472,"time":11510,"beat":2},{"sampleNumber":580171,"time":12087,"beat":1},{"sampleNumber":607856,"time":12664,"beat":2},{"sampleNumber":635556,"time":13241,"beat":1},{"sampleNumber":663240,"time":13818,"beat":2},{"sampleNumber":690941,"time":14395,"beat":1},{"sampleNumber":718625,"time":14971,"beat":2},{"sampleNumber":746326,"time":15548,"beat":1},{"sampleNumber":774010,"time":16125,"beat":2},{"sampleNumber":801710,"time":16702,"beat":1},{"sampleNumber":829395,"time":17279,"beat":2},{"sampleNumber":857095,"time":17856,"beat":1},{"sampleNumber":884780,"time":18433,"beat":2},{"sampleNumber":912480,"time":19010,"beat":1},{"sampleNumber":940165,"time":19587,"beat":2},{"sampleNumber":967857,"time":20164,"beat":3},{"sampleNumber":995557,"time":20741,"beat":1},{"sampleNumber":1023242,"time":21318,"beat":2},{"sampleNumber":1050942,"time":21895,"beat":1},{"sampleNumber":1078627,"time":22471,"beat":2},{"sampleNumber":1106327,"time":23048,"beat":1},{"sampleNumber":1134011,"time":23625,"beat":2},{"sampleNumber":1161712,"time":24202,"beat":1},{"sampleNumber":1189396,"time":24779,"beat":2},{"sampleNumber":1217097,"time":25356,"beat":1},{"sampleNumber":1244781,"time":25933,"beat":2},{"sampleNumber":1272481,"time":26510,"beat":1},{"sampleNumber":1300167,"time":27087,"beat":2},{"sampleNumber":1327866,"time":27664,"beat":1},{"sampleNumber":1355551,"time":28241,"beat":2},{"sampleNumber":1383251,"time":28818,"beat":1},{"sampleNumber":1410935,"time":29394,"beat":2},{"sampleNumber":1438636,"time":29972,"beat":1},{"sampleNumber":1466320,"time":30548,"beat":2},{"sampleNumber":1494021,"time":31125,"beat":1}]