[{"sampleNumber":35890,"time":748,"beat":1},{"sampleNumber":125459,"time":2614,"beat":2},{"sampleNumber":205459,"time":4280,"beat":3},{"sampleNumber":285467,"time":5947,"beat":1},{"sampleNumber":365459,"time":7614,"beat":2},{"sampleNumber":445477,"time":9281,"beat":3},{"sampleNumber":534078,"time":11127,"beat":1},{"sampleNumber":616241,"time":12838,"beat":2},{"sampleNumber":688521,"time":14344,"beat":3},{"sampleNumber":765732,"time":15953,"beat":1},{"sampleNumber":842357,"time":17549,"beat":2},{"sampleNumber":915881,"time":19081,"beat":3},{"sampleNumber":1066743,"time":22224,"beat":1},{"sampleNumber":1109786,"time":23121,"beat":2},{"sampleNumber":1151499,"time":23990,"beat":3},{"sampleNumber":1192000,"time":24833,"beat":1}]