[{"sampleNumber":7,"time":0,"beat":2},{"sampleNumber":20587,"time":429,"beat":1},{"sampleNumber":41150,"time":857,"beat":2},{"sampleNumber":61722,"time":1286,"beat":3},{"sampleNumber":82301,"time":1715,"beat":1},{"sampleNumber":102865,"time":2143,"beat":2},{"sampleNumber":123436,"time":2572,"beat":3},{"sampleNumber":144016,"time":3000,"beat":1},{"sampleNumber":164579,"time":3429,"beat":2},{"sampleNumber":185151,"time":3857,"beat":3},{"sampleNumber":205730,"time":4286,"beat":1},{"sampleNumber":226294,"time":4714,"beat":2},{"sampleNumber":246865,"time":5143,"beat":3},{"sampleNumber":267445,"time":5572,"beat":1},{"sampleNumber":288008,"time":6000,"beat":2},{"sampleNumber":308580,"time":6429,"beat":3},{"sampleNumber":329159,"time":6857,"beat":1},{"sampleNumber":349723,"time":7286,"beat":2},{"sampleNumber":370294,"time":7714,"beat":3},{"sampleNumber":390874,"time":8143,"beat":1},{"sampleNumber":411438,"time":8572,"beat":2},{"sampleNumber":432009,"time":9000,"beat":3},{"sampleNumber":452589,"time":9429,"beat":1},{"sampleNumber":473152,"time":9857,"beat":2},{"sampleNumber":493724,"time":10286,"beat":3},{"sampleNumber":514303,"time":10715,"beat":1},{"sampleNumber":534868,"time":11143,"beat":2},{"sampleNumber":555438,"time":11572,"beat":3},{"sampleNumber":576018,"time":12000,"beat":1},{"sampleNumber":596581,"time":12429,"beat":2},{"sampleNumber":617153,"time":12857,"beat":3},{"sampleNumber":637732,"time":13286,"beat":1},{"sampleNumber":658296,"time":13715,"beat":2},{"sampleNumber":678868,"time":14143,"beat":3},{"sampleNumber":699447,"time":14572,"beat":1},{"sampleNumber":720010,"time":15000,"beat":2},{"sampleNumber":740582,"time":15429,"beat":3},{"sampleNumber":761161,"time":15858,"beat":1},{"sampleNumber":781725,"time":16286,"beat":2},{"sampleNumber":802296,"time":16715,"beat":3},{"sampleNumber":822876,"time":17143,"beat":1},{"sampleNumber":843439,"time":17572,"beat":2},{"sampleNumber":864011,"time":18000,"beat":3},{"sampleNumber":884590,"time":18429,"beat":1},{"sampleNumber":905154,"time":18857,"beat":2},{"sampleNumber":925725,"time":19286,"beat":3},{"sampleNumber":946305,"time":19715,"beat":1},{"sampleNumber":966868,"time":20143,"beat":2},{"sampleNumber":987440,"time":20572,"beat":3},{"sampleNumber":1008019,"time":21000,"beat":1},{"sampleNumber":1028583,"time":21429,"beat":2},{"sampleNumber":1049154,"time":21857,"beat":3},{"sampleNumber":1069734,"time":22286,"beat":1},{"sampleNumber":1090298,"time":22715,"beat":2},{"sampleNumber":1110869,"time":23143,"beat":3},{"sampleNumber":1131448,"time":23572,"beat":1},{"sampleNumber":1152013,"time":24000,"beat":2},{"sampleNumber":1172583,"time":24429,"beat":3},{"sampleNumber":1193163,"time":24858,"beat":1},{"sampleNumber":1213726,"time":25286,"beat":2},{"sampleNumber":1234298,"time":25715,"beat":3},{"sampleNumber":1254877,"time":26143,"beat":1},{"sampleNumber":1275441,"time":26572,"beat":2},{"sampleNumber":1296013,"time":27000,"beat":3},{"sampleNumber":1316592,"time":27429,"beat":1},{"sampleNumber":1337155,"time":27857,"beat":2},{"sampleNumber":1357727,"time":28286,"beat":3},{"sampleNumber":1378306,"time":28715,"beat":1},{"sampleNumber":1398870,"time":29143,"beat":2},{"sampleNumber":1419441,"time":29572,"beat":3},{"sampleNumber":1440021,"time":30000,"beat":1},{"sampleNumber":1460584,"time":30429,"beat":2},{"sampleNumber":1481156,"time":30857,"beat":3},{"sampleNumber":1501735,"time":31286,"beat":1},{"sampleNumber":1522299,"time":31715,"beat":2},{"sampleNumber":1542870,"time":32143,"beat":3},{"sampleNumber":1563450,"time":32572,"beat":1},{"sampleNumber":1584013,"time":33000,"beat":2},{"sampleNumber":1604585,"time":33429,"beat":3}]