[{"sampleNumber":27495,"time":573,"beat":2},{"sampleNumber":67496,"time":1406,"beat":3},{"sampleNumber":99503,"time":2073,"beat":1},{"sampleNumber":131496,"time":2740,"beat":2},{"sampleNumber":163494,"time":3406,"beat":3},{"sampleNumber":195494,"time":4073,"beat":4},{"sampleNumber":227502,"time":4740,"beat":1},{"sampleNumber":259495,"time":5406,"beat":2},{"sampleNumber":291494,"time":6073,"beat":3},{"sampleNumber":323495,"time":6739,"beat":4},{"sampleNumber":355502,"time":7406,"beat":1},{"sampleNumber":387494,"time":8073,"beat":2},{"sampleNumber":419495,"time":8739,"beat":3},{"sampleNumber":451494,"time":9406,"beat":4},{"sampleNumber":483501,"time":10073,"beat":1},{"sampleNumber":515494,"time":10739,"beat":2},{"sampleNumber":547494,"time":11406,"beat":3},{"sampleNumber":579494,"time":12073,"beat":4},{"sampleNumber":611501,"time":12740,"beat":1}]