[{"sampleNumber":15,"time":0,"beat":1},{"sampleNumber":18007,"time":375,"beat":2},{"sampleNumber":36007,"time":750,"beat":3},{"sampleNumber":54007,"time":1125,"beat":4},{"sampleNumber":72015,"time":1500,"beat":1},{"sampleNumber":90008,"time":1875,"beat":2},{"sampleNumber":108007,"time":2250,"beat":3},{"sampleNumber":126007,"time":2625,"beat":4},{"sampleNumber":144015,"time":3000,"beat":1},{"sampleNumber":162008,"time":3375,"beat":2},{"sampleNumber":180007,"time":3750,"beat":3},{"sampleNumber":198007,"time":4125,"beat":4},{"sampleNumber":216015,"time":4500,"beat":1},{"sampleNumber":234008,"time":4875,"beat":2},{"sampleNumber":252006,"time":5250,"beat":3},{"sampleNumber":270006,"time":5625,"beat":4},{"sampleNumber":288014,"time":6000,"beat":1},{"sampleNumber":306603,"time":6388,"beat":2},{"sampleNumber":326574,"time":6804,"beat":3},{"sampleNumber":348277,"time":7256,"beat":4},{"sampleNumber":370896,"time":7727,"beat":1},{"sampleNumber":388889,"time":8102,"beat":2},{"sampleNumber":406888,"time":8477,"beat":3},{"sampleNumber":424888,"time":8852,"beat":4},{"sampleNumber":442896,"time":9227,"beat":1},{"sampleNumber":460888,"time":9602,"beat":2},{"sampleNumber":478887,"time":9977,"beat":3},{"sampleNumber":496887,"time":10352,"beat":4},{"sampleNumber":514895,"time":10727,"beat":1},{"sampleNumber":532888,"time":11102,"beat":2},{"sampleNumber":550887,"time":11477,"beat":3},{"sampleNumber":568887,"time":11852,"beat":4},{"sampleNumber":586895,"time":12227,"beat":1},{"sampleNumber":604887,"time":12602,"beat":2},{"sampleNumber":622887,"time":12977,"beat":3},{"sampleNumber":640887,"time":13352,"beat":4},{"sampleNumber":658895,"time":13727,"beat":1},{"sampleNumber":676887,"time":14102,"beat":2},{"sampleNumber":694887,"time":14477,"beat":3},{"sampleNumber":712887,"time":14852,"beat":4},{"sampleNumber":730894,"time":15227,"beat":1},{"sampleNumber":748886,"time":15602,"beat":2},{"sampleNumber":766886,"time":15977,"beat":3},{"sampleNumber":784886,"time":16352,"beat":4},{"sampleNumber":802894,"time":16727,"beat":1},{"sampleNumber":820886,"time":17102,"beat":2},{"sampleNumber":838887,"time":17477,"beat":3},{"sampleNumber":856886,"time":17852,"beat":4},{"sampleNumber":874894,"time":18227,"beat":1},{"sampleNumber":892886,"time":18602,"beat":2},{"sampleNumber":910886,"time":18977,"beat":3},{"sampleNumber":928886,"time":19352,"beat":4}]