[{"sampleNumber":141,"time":3,"beat":2},{"sampleNumber":34032,"time":709,"beat":1},{"sampleNumber":67906,"time":1415,"beat":2},{"sampleNumber":101797,"time":2121,"beat":1},{"sampleNumber":135671,"time":2826,"beat":2},{"sampleNumber":169562,"time":3533,"beat":1},{"sampleNumber":203436,"time":4238,"beat":2},{"sampleNumber":237327,"time":4944,"beat":1},{"sampleNumber":271201,"time":5650,"beat":2},{"sampleNumber":305092,"time":6356,"beat":1},{"sampleNumber":338966,"time":7062,"beat":2},{"sampleNumber":372856,"time":7768,"beat":1},{"sampleNumber":406731,"time":8474,"beat":2},{"sampleNumber":440621,"time":9180,"beat":1},{"sampleNumber":474497,"time":9885,"beat":2},{"sampleNumber":508386,"time":10591,"beat":1},{"sampleNumber":542261,"time":11297,"beat":2},{"sampleNumber":576151,"time":12003,"beat":1},{"sampleNumber":610026,"time":12709,"beat":2},{"sampleNumber":643916,"time":13415,"beat":1},{"sampleNumber":677791,"time":14121,"beat":2},{"sampleNumber":711681,"time":14827,"beat":1}]